pytiger/__init__.py
pytiger/logging/__init__.py
pytiger/logging/config.py
pytiger/logging/syslog.py
pytiger/logging/test_config.py
pytiger/logging/test_syslog.py
pytiger/monitoring/__init__.py
pytiger/monitoring/monitoringcheck.py
pytiger/monitoring/test_monitoringcheck.py
pytiger/utils/__init__.py
pytiger/utils/decorators.py
pytiger/utils/filesystem.py
pytiger/utils/plugins.py
pytiger/utils/plugins_imp.py
pytiger/utils/plugins_importlib.py
pytiger/utils/test_decorators.py
pytiger/utils/test_filesystem.py
pytiger/utils/test_plugins.py
pytiger-2.0.2.dist-info/licenses/COPYING
pytiger-2.0.2.dist-info/METADATA
pytiger-2.0.2.dist-info/WHEEL
pytiger-2.0.2.dist-info/top_level.txt
pytiger-2.0.2.dist-info/RECORD
