Metadata-Version: 2.4
Name: pytiger
Version: 2.0.2
Summary: Tiger Computing Ltd Python Utilities
Author: Tiger Computing Ltd
Author-email: info@tiger-computing.co.uk
License-File: COPYING
Dynamic: author
Dynamic: author-email
Dynamic: license-file
Dynamic: summary
